<?xml version="1.0" encoding="utf-8" ?><dwsync><file name="blblblbl.swf" local="-4469560804663885824" remote="-4469572817687412736" testing="0" /><file name="didoodidoo.swf" local="-4469562973622370304" remote="-4469572817687412736" testing="0" /><file name="hfuuuh.swf" local="-4469560525491011584" remote="-4469572817687412736" testing="0" /><file name="iuu_uui.swf" local="-4469561483268718592" remote="-4469572817687412736" testing="0" /><file name="mingus.swf" local="-4469562879133089792" remote="-4469572817687412736" testing="0" /><file name="pouyyi.swf" local="-4469561070951858176" remote="-4469572559989374976" testing="0" /><file name="taklantiioo.swf" local="-4469561740966756352" remote="-4469572559989374976" testing="0" /><file name="tictac.swf" local="-4469562539830673408" remote="-4469572559989374976" testing="0" /><file name="tratitatatii.swf" local="-4469562286427602944" remote="-4469572559989374976" testing="0" /></dwsync>